mark3
