Metadata-Version: 1.0
Name: mark3
Version: 0.1.2
Summary: A lightweight markdown to html converter.
Home-page: https://bitbucket.org/jlm/mark3
Author: Joseph Marshall
Author-email: marshallpenguin@gmail.com
License: UNKNOWN
Keywords: markdown html
Platform: UNKNOWN
Classifier: Programming Language :: Python
Classifier: Programming Language :: Python :: 2.7
Classifier: Programming Language :: Python :: 3
Classifier: Development Status :: 4 - Beta
Classifier: Intended Audience :: Developers
Classifier: License :: OSI Approved :: MIT License
Classifier: Operating System :: OS Independent
Classifier: Topic :: Text Processing :: Markup :: HTML
